LICENSE.txt
NEWS.rst
README.rst
setup.py
gtabview/__init__.py
gtabview/compat.py
gtabview/dataio.py
gtabview/models.py
gtabview/qtpy.py
gtabview/viewer.py
gtabview.egg-info/PKG-INFO
gtabview.egg-info/SOURCES.txt
gtabview.egg-info/dependency_links.txt
gtabview.egg-info/entry_points.txt
gtabview.egg-info/pbr.json
gtabview.egg-info/requires.txt
gtabview.egg-info/top_level.txt
gtabview_cli/__init__.py
gtabview_cli/gtabview.py
sample/data_ohlcv.csv
sample/excel.xls
sample/multiindex_H2_I4.csv
sample/pandas-example.py
sample/test_latin-1.csv
sample/unicode-example-utf8.txt
tests/__init__.py
tests/test_dataio.py
tests/test_models.py
tests/test_view.py
tests/data/empty-line-1.txt
tests/data/empty-line-2.txt
tests/data/hash-headers.txt
tests/data/not-xls.xls
tests/data/simple.csv
tests/data/simple.xls