Metadata-Version: 2.1
Name: gtabview
Version: 0.10.1
Summary: A simple graphical tabular data viewer
Home-page: https://github.com/TabViewer/gtabview
Author: Yuri D'Elia
Author-email: wavexx@thregr.org
License: MIT
Keywords: data spreadsheet view viewer csv comma separated values
Platform: UNKNOWN
Classifier: Development Status :: 5 - Production/Stable
Classifier: Environment :: Win32 (MS Windows)
Classifier: Environment :: MacOS X
Classifier: Environment :: X11 Applications :: Qt
Classifier: Intended Audience :: Science/Research
Classifier: License :: OSI Approved :: MIT License
Classifier: Operating System :: OS Independent
Classifier: Programming Language :: Python
Classifier: Programming Language :: Python :: 2.7
Classifier: Programming Language :: Python :: 3
Classifier: Topic :: Office/Business :: Financial :: Spreadsheet
Classifier: Topic :: Scientific/Engineering :: Visualization
Classifier: Topic :: Software Development :: User Interfaces
Classifier: Topic :: Software Development :: Widget Sets
Classifier: Topic :: Utilities
Provides-Extra: test
